{
  "str": 0,
  "int": 1,
  "Optional[Dict]": 2,
  "float": 3,
  "Optional[str]": 4,
  "Path": 5,
  "bool": 6,
  "List[str]": 7,
  "Optional[Path]": 8,
  "Optional[GitIgnoreMatcher]": 9,
  "Tuple[List[Dict], List[Dict], List[Dict]]": 10,
  "tuple": 11,
  "Tuple[List[Tuple[int, int, str, float]], List[Tuple[int, int, str, float]]]": 12,
  "List[Tuple[int, int, str, float]]": 13,
  "List[Tuple[int, int]]": 14,
  "List[Dict]": 15,
  "Dict[str, Tuple[str, str, str]]": 16,
  "Dict[int, str]": 17,
  "np.ndarray": 18,
  "set": 19,
  "List[List[int]]": 20,
  "KeyedVectors": 21,
  "List[List[str]]": 22,
  "Tuple[np.ndarray, KeyedVectors]": 23,
  "Tuple[Dict[str, int], List[Dict], Dict[str, List[str]], Dict[str, Tuple[str, str, str]]]": 24,
  "Tuple[List[Tuple[int, int, str, float]], int]": 25,
  "Dict[str, int]": 26,
  "Tuple[Dict[int, Dict[str, int]], Dict[str, int]]": 27,
  "Dict[int, Tuple[str, int]]": 28,
  "Optional[int]": 29,
  "ast.AST": 30,
  "Set[str]": 31,
  "List[np.ndarray]": 32,
  "Tuple[np.ndarray, np.ndarray, np.ndarray]": 33,
  "sparse.csr_matrix": 34,
  "Optional[datetime]": 35,
  "dict": 36,
  "'cusp.spmatrix'": 37,
  "sparse.spmatrix": 38,
  "Tuple[List[Tuple[int, int, str, float]], int, Dict[str, int]]": 39,
  "Dict[str, List[str]]": 40,
  "Tuple[np.ndarray, np.ndarray]": 41,
  "Tuple[np.ndarray, np.ndarray, int, Dict[str, int], List[Tuple[int, int, str, float]]]": 42,
  "Optional[bool]": 43,
  "Tuple[int, int, int]": 44,
  "Dict": 45,
  "List[Tuple[str, float]]": 46,
  "Dict[str, float]": 47,
  "Optional[Set[str]]": 48,
  "Optional[np.ndarray]": 49,
  "Tuple[List[str], List[str]]": 50,
  "Tuple[str, str, str]": 51,
  "Dict[int, Dict[str, int]]": 52,
  "Tuple[sparse.csr_matrix, Dict[str, int]]": 53,
  "Tuple[np.ndarray, np.ndarray, Dict[str, int]]": 54,
  "Optional": 55,
  "List": 56,
  "GitIgnoreMatcher": 57,
  "Tuple": 58,
  "List[Dict": 59,
  "List[Tuple[int": 60,
  "Tuple[int": 61,
  "Tuple[str": 62,
  "List[int": 63,
  "List[str": 64,
  "Dict[str": 65,
  "int]": 66,
  "Dict[int": 67,
  "Set": 68,
  "datetime": 69,
  "Set[str": 70
}